lazydoc/__init__.py
lazydoc/__main__.py
lazydoc/cli.py
lazydoc/lazydoc.py
lazydoc-1.0.1.dist-info/DESCRIPTION.rst
lazydoc-1.0.1.dist-info/METADATA
lazydoc-1.0.1.dist-info/RECORD
lazydoc-1.0.1.dist-info/WHEEL
lazydoc-1.0.1.dist-info/entry_points.txt
lazydoc-1.0.1.dist-info/metadata.json
lazydoc-1.0.1.dist-info/top_level.txt
