Metadata-Version: 2.0
Name: lazydoc
Version: 1.0.1
Summary: UNKNOWN
Home-page: http://github.com/chappers/lazydoc
Author: Chapman Siu
Author-email: chpmn.siu@gmail.com
License: UNKNOWN
Platform: UNKNOWN
Classifier: Development Status :: 5 - Production/Stable
Classifier: Environment :: Plugins
Classifier: Intended Audience :: Developers
Classifier: License :: OSI Approved :: MIT License
Classifier: Operating System :: OS Independent
Classifier: Programming Language :: Python
Classifier: Topic :: Documentation
Classifier: Topic :: Documentation :: Sphinx
Classifier: Topic :: Text Processing
Classifier: Topic :: Utilities
Classifier: Framework :: Sphinx
